arduinopy/__init__.py
arduinopy/arduino.py
arduinopy-0.1.0.dist-info/LICENSE.txt
arduinopy-0.1.0.dist-info/METADATA
arduinopy-0.1.0.dist-info/WHEEL
arduinopy-0.1.0.dist-info/RECORD
