Metadata-Version: 2.1
Name: arduinopy
Version: 0.1.0
Summary: A light-weight Python library that provides a serial bridge for communicating with Arduino microcontroller boards.
Home-page: https://github.com/samiralavi/arduinopy
License: MIT
Author: Seyed Amir Alavi
Author-email: seydamir@gmail.com
Requires-Python: >=3.8,<4.0
Classifier: License :: OSI Approved :: MIT License
Classifier: Programming Language :: Python :: 3
Classifier: Programming Language :: Python :: 3.8
Classifier: Programming Language :: Python :: 3.9
Classifier: Programming Language :: Python :: 3.10
Classifier: Programming Language :: Python :: 3.11
Requires-Dist: pyserial (>=3.5,<4.0)
Project-URL: Repository, https://github.com/samiralavi/arduinopy
